formulate/AST.py
formulate/__init__.py
formulate/_version.py
formulate/cli.py
formulate/exceptions.py
formulate/identifiers.py
formulate/toast.py
formulate/resources/numexpr_grammar.lark
formulate/resources/root_grammar.lark
formulate-1.0.1.dist-info/METADATA
formulate-1.0.1.dist-info/WHEEL
formulate-1.0.1.dist-info/entry_points.txt
formulate-1.0.1.dist-info/licenses/LICENSE
formulate-1.0.1.dist-info/RECORD
