Metadata-Version: 2.4
Name: formulate
Version: 1.0.1
Summary:  Easy conversions between different styles of expressions
Project-URL: Homepage, https://github.com/Scikit-HEP/formulate
Project-URL: Bug Tracker, https://github.com/Scikit-HEP/formulate/issues
Project-URL: Discussions, https://github.com/Scikit-HEP/formulate/discussions
Project-URL: Changelog, https://github.com/Scikit-HEP/formulate/releases
Author-email: Chris Burr <c.b@cern.ch>, Aryan Roy <aryanroy5678@gmail.com>, Jonas Eschle <jonas.eschle@gmail.com>
Maintainer-email: The Scikit-HEP admins <scikit-hep-admins@googlegroups.com>
License-File: LICENSE
Classifier: Development Status :: 1 - Planning
Classifier: Intended Audience :: Developers
Classifier: Intended Audience :: Science/Research
Classifier: License :: OSI Approved :: BSD License
Classifier: Operating System :: OS Independent
Classifier: Programming Language :: Python
Classifier: Programming Language :: Python :: 3.10
Classifier: Programming Language :: Python :: 3.11
Classifier: Programming Language :: Python :: 3.12
Classifier: Programming Language :: Python :: 3.13
Classifier: Programming Language :: Python :: 3.14
Classifier: Topic :: Scientific/Engineering
Classifier: Typing :: Typed
Requires-Python: >=3.10
Requires-Dist: hepunits
Requires-Dist: lark>=1.3
Requires-Dist: ordered-set
Provides-Extra: all
Requires-Dist: hypothesis; extra == 'all'
Requires-Dist: jupyter-sphinx>=0.3.2; extra == 'all'
Requires-Dist: myst-parser>=0.13; extra == 'all'
Requires-Dist: numexpr; extra == 'all'
Requires-Dist: numpy; extra == 'all'
Requires-Dist: pre-commit; extra == 'all'
Requires-Dist: pytest-cov>=3; extra == 'all'
Requires-Dist: pytest>=6; extra == 'all'
Requires-Dist: sphinx-autodoc-typehints; extra == 'all'
Requires-Dist: sphinx-book-theme>=0.1.0; extra == 'all'
Requires-Dist: sphinx-copybutton; extra == 'all'
Requires-Dist: sphinx-rtd-theme; extra == 'all'
Requires-Dist: sphinx>=4.0; extra == 'all'
Provides-Extra: dev
Requires-Dist: hypothesis; extra == 'dev'
Requires-Dist: jupyter-sphinx>=0.3.2; extra == 'dev'
Requires-Dist: myst-parser>=0.13; extra == 'dev'
Requires-Dist: numexpr; extra == 'dev'
Requires-Dist: numpy; extra == 'dev'
Requires-Dist: pre-commit; extra == 'dev'
Requires-Dist: pytest-cov>=3; extra == 'dev'
Requires-Dist: pytest>=6; extra == 'dev'
Requires-Dist: sphinx-autodoc-typehints; extra == 'dev'
Requires-Dist: sphinx-book-theme>=0.1.0; extra == 'dev'
Requires-Dist: sphinx-copybutton; extra == 'dev'
Requires-Dist: sphinx-rtd-theme; extra == 'dev'
Requires-Dist: sphinx>=4.0; extra == 'dev'
Provides-Extra: docs
Requires-Dist: jupyter-sphinx>=0.3.2; extra == 'docs'
Requires-Dist: myst-parser>=0.13; extra == 'docs'
Requires-Dist: numexpr; extra == 'docs'
Requires-Dist: sphinx-autodoc-typehints; extra == 'docs'
Requires-Dist: sphinx-book-theme>=0.1.0; extra == 'docs'
Requires-Dist: sphinx-copybutton; extra == 'docs'
Requires-Dist: sphinx-rtd-theme; extra == 'docs'
Requires-Dist: sphinx>=4.0; extra == 'docs'
Provides-Extra: test
Requires-Dist: hypothesis; extra == 'test'
Requires-Dist: numpy; extra == 'test'
Requires-Dist: pytest-cov>=3; extra == 'test'
Requires-Dist: pytest>=6; extra == 'test'
